odoo/addons/l10n_mx_sat_reference/README.rst
odoo/addons/l10n_mx_sat_reference/__init__.py
odoo/addons/l10n_mx_sat_reference/__manifest__.py
odoo/addons/l10n_mx_sat_reference/data/sat.receipt.type.csv
odoo/addons/l10n_mx_sat_reference/data/sat.receipt.use.csv
odoo/addons/l10n_mx_sat_reference/data/sat.relation.type.csv
odoo/addons/l10n_mx_sat_reference/i18n/l10n_mx_sat_reference.pot
odoo/addons/l10n_mx_sat_reference/models/__init__.py
odoo/addons/l10n_mx_sat_reference/models/sat_receipt_type.py
odoo/addons/l10n_mx_sat_reference/models/sat_receipt_use.py
odoo/addons/l10n_mx_sat_reference/models/sat_relation_type.py
odoo/addons/l10n_mx_sat_reference/readme/CONTRIBUTORS.rst
odoo/addons/l10n_mx_sat_reference/readme/CREDITS.rst
odoo/addons/l10n_mx_sat_reference/readme/DESCRIPTION.rst
odoo/addons/l10n_mx_sat_reference/readme/USAGE.rst
odoo/addons/l10n_mx_sat_reference/security/ir.model.access.csv
odoo/addons/l10n_mx_sat_reference/static/description/icon.png
odoo/addons/l10n_mx_sat_reference/static/description/index.html
odoo/addons/l10n_mx_sat_reference/views/sat_receipt_type_view.xml
odoo/addons/l10n_mx_sat_reference/views/sat_receipt_use_view.xml
odoo/addons/l10n_mx_sat_reference/views/sat_relation_type_view.xml
odoo13_addon_l10n_mx_sat_reference-13.0.1.0.1.dev12.dist-info/METADATA
odoo13_addon_l10n_mx_sat_reference-13.0.1.0.1.dev12.dist-info/WHEEL
odoo13_addon_l10n_mx_sat_reference-13.0.1.0.1.dev12.dist-info/top_level.txt
odoo13_addon_l10n_mx_sat_reference-13.0.1.0.1.dev12.dist-info/RECORD
