Metadata-Version: 2.1
Name: odoo13-addon-l10n-mx-sat-reference
Version: 13.0.1.0.1.dev12
Summary: This module provides the list of references to documents that the Mexican tax authority, Servicio de Administración Tributaria (SAT) requires to be signed/transferred.
Home-page: https://github.com/OCA/l10n-mexico
Author: Open Source Integrators, Serpent Consulting Services Pvt. Ltd., Odoo Community Association (OCA)
Author-email: support@odoo-community.org
License: AGPL-3
Platform: UNKNOWN
Classifier: Programming Language :: Python
Classifier: Framework :: Odoo
Classifier: Framework :: Odoo :: 13.0
Classifier: License :: OSI Approved :: GNU Affero General Public License v3
Classifier: Development Status :: 4 - Beta
Requires-Python: >=3.5
Requires-Dist: odoo <13.1dev,>=13.0a
